setup.cfg
setup.py
mypc/__init__.py
mypc/main.py
mypc.egg-info/PKG-INFO
mypc.egg-info/SOURCES.txt
mypc.egg-info/dependency_links.txt
mypc.egg-info/entry_points.txt
mypc.egg-info/top_level.txt