Metadata-Version: 1.0
Name: mypc
Version: 0.0.1
Summary: Open "This PC" on Windows.
Home-page: https://github.com/Frederick-S/mypc
Author: UNKNOWN
Author-email: UNKNOWN
License: UNKNOWN
Platform: UNKNOWN
